README.md
setup.py
c_sharepoint/__init__.py
c_sharepoint.egg-info/PKG-INFO
c_sharepoint.egg-info/SOURCES.txt
c_sharepoint.egg-info/dependency_links.txt
c_sharepoint.egg-info/requires.txt
c_sharepoint.egg-info/top_level.txt