Metadata-Version: 2.1
Name: c-sharepoint
Version: 0.0.4
Summary: c_sharepoint
Home-page: https://github.com/EvanFanFan/c_sharepoint
Author: evanyang
Author-email: lightyiyi@qq.com
License: MIT tencent_message
Platform: UNKNOWN
